ups_turkey/__init__.py
ups_turkey/encoders.py
ups_turkey/exceptions.py
ups_turkey/helpers.py
ups_turkey/ups.py
ups_turkey-0.2.0.dist-info/LICENSE.md
ups_turkey-0.2.0.dist-info/METADATA
ups_turkey-0.2.0.dist-info/WHEEL
ups_turkey-0.2.0.dist-info/top_level.txt
ups_turkey-0.2.0.dist-info/RECORD
