Metadata-Version: 2.1
Name: ups-turkey
Version: 0.2.0
Summary: Easy integration for UPS Turkey
Home-page: https://github.com/EfraimGENC/ups-turkey
Download-URL: https://github.com/EfraimGENC/ups-turkey/archive/refs/tags/v0.2.0.tar.gz
Author: Efraim GENC
Author-email: info@kavimdigital.com
License: MIT
Keywords: ups_turkey,ups-turkey,ups,turkey,shipment
Classifier: Programming Language :: Python :: 3
Classifier: License :: OSI Approved :: MIT License
Classifier: Operating System :: OS Independent
License-File: LICENSE.md
Requires-Dist: zeep (>=4.1.0)
